Metadata-Version: 2.1
Name: bytefield
Version: 1.0.1
Summary: Parse binary data using declarative field layout and native Python properties
Home-page: https://github.com/donadigo/bytefield
Download-URL: https://github.com/donadigo/bytefield
Author: donadigo
Author-email: donadigo@gmail.com
License: MIT
Keywords: struct,bytefield,bytearray
Platform: UNKNOWN
Classifier: Development Status :: 4 - Beta
Classifier: Intended Audience :: Developers
Classifier: Topic :: Software Development :: Build Tools
Classifier: License :: OSI Approved :: MIT License
Classifier: Programming Language :: Python :: 3
Classifier: Programming Language :: Python :: 3.4
Classifier: Programming Language :: Python :: 3.5
Classifier: Programming Language :: Python :: 3.6
License-File: LICENSE
